jinja2-stubs/METADATA.toml
jinja2-stubs/__init__.pyi
jinja2-stubs/_compat.pyi
jinja2-stubs/_stringdefs.pyi
jinja2-stubs/bccache.pyi
jinja2-stubs/compiler.pyi
jinja2-stubs/constants.pyi
jinja2-stubs/debug.pyi
jinja2-stubs/defaults.pyi
jinja2-stubs/environment.pyi
jinja2-stubs/exceptions.pyi
jinja2-stubs/ext.pyi
jinja2-stubs/filters.pyi
jinja2-stubs/lexer.pyi
jinja2-stubs/loaders.pyi
jinja2-stubs/meta.pyi
jinja2-stubs/nodes.pyi
jinja2-stubs/optimizer.pyi
jinja2-stubs/parser.pyi
jinja2-stubs/runtime.pyi
jinja2-stubs/sandbox.pyi
jinja2-stubs/tests.pyi
jinja2-stubs/utils.pyi
jinja2-stubs/visitor.pyi
types_Jinja2-2.11.9.dist-info/METADATA
types_Jinja2-2.11.9.dist-info/WHEEL
types_Jinja2-2.11.9.dist-info/top_level.txt
types_Jinja2-2.11.9.dist-info/RECORD
