Metadata-Version: 2.1
Name: types-Jinja2
Version: 2.11.9
Summary: Typing stubs for Jinja2
Home-page: https://github.com/python/typeshed
License: Apache-2.0 license
Platform: UNKNOWN
Classifier: License :: OSI Approved :: Apache Software License
Classifier: Typing :: Typed
